<?xml version="1.0"?>
<!DOCTYPE hibernate-mapping PUBLIC "-//Hibernate/Hibernate Mapping DTD 3.0//EN"
"http://hibernate.sourceforge.net/hibernate-mapping-3.0.dtd">
<!-- Generated 31-ene-2015 11:15:40 by Hibernate Tools 3.4.0.CR1 -->
<hibernate-mapping>
    <class name="com.vcortes.canjehoras.model.Preferencias" table="preferencias" >
        <id name="id" type="java.lang.Integer">
            <column name="ID" />
            <generator class="identity" />
        </id>
        <many-to-one name="usuario" class="com.vcortes.canjehoras.model.Usuario" fetch="select">
            <column name="ID_USUARIO" not-null="true" />
        </many-to-one>
        <many-to-one name="categoria" class="com.vcortes.canjehoras.model.Categoria" fetch="select">
            <column name="ID_CATEGORIA" not-null="true" />
        </many-to-one>
        <many-to-one name="provincia" class="com.vcortes.canjehoras.model.Provincia" fetch="select">
            <column name="ID_PROVINCIA" not-null="true" />
        </many-to-one>
    </class>
</hibernate-mapping>
